{
  "sections": {
    "collections_hero": {
      "type": "collections-page-hero",
      "settings": {
        "page_title": "Collections",
        "eyebrow": "All Collections",
        "heading_line1": "Curated picks for",
        "heading_line2": "every corner of life.",
        "subheading": "From kitchen essentials to wellness staples and pet-care must-haves — every product hand-tested by our team.",
        "stat_1_num": "8",
        "stat_1_label": "Collections",
        "stat_2_num": "240+",
        "stat_2_label": "Products",
        "stat_3_num": "12.4k",
        "stat_3_label": "Happy Customers",
        "stat_4_num": "4.8★",
        "stat_4_label": "Avg. Rating"
      }
    },
    "collections_grid": {
      "type": "collections-featured-grid",
      "settings": {
        "section_label": "Browse the Shop",
        "section_title": "Pick your category.",
        "section_body": "Eight collections, all built around things that genuinely make daily life better.",
        "show_sort": true,
        "max_collections": 12
      }
    },
    "collections_help_strip": {
      "type": "collections-help-strip",
      "blocks": {
        "cell_1": {
          "type": "cell",
          "settings": {
            "icon": "shipping",
            "title": "Free EU shipping",
            "body": "On orders over €40 — delivered in 5–9 days"
          }
        },
        "cell_2": {
          "type": "cell",
          "settings": {
            "icon": "returns",
            "title": "30-day returns",
            "body": "Send anything back, no questions asked"
          }
        },
        "cell_3": {
          "type": "cell",
          "settings": {
            "icon": "secure",
            "title": "Secure checkout",
            "body": "Stripe-encrypted payments, every order"
          }
        },
        "cell_4": {
          "type": "cell",
          "settings": {
            "icon": "rating",
            "title": "4.8★ from 12,400+",
            "body": "Real reviews on Trustpilot & Google"
          }
        }
      },
      "block_order": [
        "cell_1",
        "cell_2",
        "cell_3",
        "cell_4"
      ]
    },
    "collections_editorial": {
      "type": "collections-editorial",
      "settings": {
        "vis_tag": "Editor’s pick",
        "label": "Bundle Up & Save",
        "title_line1": "The Pet Owner Bundle.",
        "title_line2": "3 essentials, one price.",
        "body": "Lint brush + anti-static glove + furniture roller. Curated for cat and dog parents — saves €18 vs. buying separately.",
        "button_label": "Shop the bundle",
        "button_url": ""
      }
    }
  },
  "order": [
    "collections_hero",
    "collections_grid",
    "collections_help_strip",
    "collections_editorial"
  ]
}